aliyunsdkairec/__init__.py
aliyunsdkairec/endpoint.py
aliyunsdkairec/request/__init__.py
aliyunsdkairec/request/v20201126/AttachDatasetRequest.py
aliyunsdkairec/request/v20201126/AttachIndexVersionRequest.py
aliyunsdkairec/request/v20201126/CheckRankingModelReachableRequest.py
aliyunsdkairec/request/v20201126/CloneExperimentRequest.py
aliyunsdkairec/request/v20201126/CloneSampleRequest.py
aliyunsdkairec/request/v20201126/ColdStartRankRequest.py
aliyunsdkairec/request/v20201126/CreateCustomAnalysisTaskRequest.py
aliyunsdkairec/request/v20201126/CreateCustomSampleRequest.py
aliyunsdkairec/request/v20201126/CreateDataDiagnoseTaskRequest.py
aliyunsdkairec/request/v20201126/CreateExtraDataSourceRequest.py
aliyunsdkairec/request/v20201126/CreateFilteringAlgorithmRequest.py
aliyunsdkairec/request/v20201126/CreateFlowControlTaskRequest.py
aliyunsdkairec/request/v20201126/CreateInstanceRequest.py
aliyunsdkairec/request/v20201126/CreateRankingModelRequest.py
aliyunsdkairec/request/v20201126/CreateRankingModelTemplateRequest.py
aliyunsdkairec/request/v20201126/CreateRankingSystemRequest.py
aliyunsdkairec/request/v20201126/CreateRuleRequest.py
aliyunsdkairec/request/v20201126/CreateSampleFormatConfigRequest.py
aliyunsdkairec/request/v20201126/CreateSceneRequest.py
aliyunsdkairec/request/v20201126/CreateUmengTokenRequest.py
aliyunsdkairec/request/v20201126/DecribeRankingModelRequest.py
aliyunsdkairec/request/v20201126/DeleteDataSetRequest.py
aliyunsdkairec/request/v20201126/DeleteExperimentRequest.py
aliyunsdkairec/request/v20201126/DeleteExtraDataSourceRequest.py
aliyunsdkairec/request/v20201126/DeleteFilteringAlgorithmRequest.py
aliyunsdkairec/request/v20201126/DeleteFlowControlTaskRequest.py
aliyunsdkairec/request/v20201126/DeleteRankingModelRequest.py
aliyunsdkairec/request/v20201126/DeleteRankingModelTemplateRequest.py
aliyunsdkairec/request/v20201126/DeleteRankingModelVersionRequest.py
aliyunsdkairec/request/v20201126/DeleteRankingSystemRequest.py
aliyun_python_sdk_airec-2.1.0.dist-info/LICENSE
aliyun_python_sdk_airec-2.1.0.dist-info/METADATA
aliyun_python_sdk_airec-2.1.0.dist-info/WHEEL
aliyun_python_sdk_airec-2.1.0.dist-info/top_level.txt
aliyun_python_sdk_airec-2.1.0.dist-info/RECORD
